[{"line":2,"elements":[{"line":4,"name":"","description":"","type":"background","keyword":"Background","steps":[{"result":{"duration":997600,"status":"passed"},"line":5,"name":"launch the browser from config variables","match":{"location":"stepDefinitions.MainSteps.launch_the_browser_from_config_variables()"},"keyword":"When "},{"result":{"duration":1000700,"status":"passed"},"line":6,"name":"hit the home page url of banking site","match":{"location":"stepDefinitions.MainSteps.hit_the_home_page_url_of_banking_site()"},"keyword":"And "}]},{"start_timestamp":"2024-12-15T08:59:42.459Z","before":[{"result":{"duration":3242000,"status":"passed"},"match":{"location":"stepDefinitions.hooks.getDataForNet()"}}],"line":10,"name":"Userpage login","description":"","id":"application-login;userpage-login","after":[{"result":{"duration":1193000,"status":"passed"},"match":{"location":"stepDefinitions.hooks.tear()"}}],"type":"scenario","keyword":"Scenario","steps":[{"result":{"status":"passed"},"line":12,"name":"User is on NetBanking login page","match":{"location":"stepDefinitions.MainSteps.user_is_not_net_banking_login_page()"},"keyword":"Given "},{"result":{"status":"passed"},"line":13,"name":"User login into application with \"user\" and password \"9087\"","match":{"arguments":[{"val":"\"user\"","offset":33},{"val":"\"9087\"","offset":53}],"location":"stepDefinitions.MainSteps.user_login_into_application_with_and_password(java.lang.String,java.lang.String)"},"keyword":"When "},{"result":{"status":"passed"},"line":14,"name":"Home Page is displayed","match":{"location":"stepDefinitions.MainSteps.home_page_is_displayed()"},"keyword":"Then "},{"result":{"status":"passed"},"line":15,"name":"Card are displayed","match":{"location":"stepDefinitions.MainSteps.card_are_displayed()"},"keyword":"And "}],"tags":[{"name":"@tag"},{"name":"@MobileTest"},{"name":"@NetBanking"}]},{"line":4,"name":"","description":"","type":"background","keyword":"Background","steps":[{"result":{"status":"passed"},"line":5,"name":"launch the browser from config variables","match":{"location":"stepDefinitions.MainSteps.launch_the_browser_from_config_variables()"},"keyword":"When "},{"result":{"duration":1004200,"status":"passed"},"line":6,"name":"hit the home page url of banking site","match":{"location":"stepDefinitions.MainSteps.hit_the_home_page_url_of_banking_site()"},"keyword":"And "}]},{"start_timestamp":"2024-12-15T08:59:42.522Z","before":[{"result":{"status":"passed"},"match":{"location":"stepDefinitions.hooks.getDataForMortage()"}}],"line":28,"name":"Userpage login multiple users","description":"","id":"application-login;userpage-login-multiple-users;;2","after":[{"result":{"duration":998800,"status":"passed"},"match":{"location":"stepDefinitions.hooks.tear()"}}],"type":"scenario","keyword":"Scenario Outline","steps":[{"result":{"status":"passed"},"line":21,"name":"User is on NetBanking login page","match":{"location":"stepDefinitions.MainSteps.user_is_not_net_banking_login_page()"},"keyword":"Given "},{"result":{"status":"passed"},"line":22,"name":"User login into application with debituser and password \"hello12\"","match":{"arguments":[{"val":"debituser","offset":33},{"val":"\"hello12\"","offset":56}],"location":"stepDefinitions.MainSteps.user_login_into_application_with_and_password(java.lang.String,java.lang.String)"},"keyword":"When "},{"result":{"status":"passed"},"line":23,"name":"Home Page is displayed","match":{"location":"stepDefinitions.MainSteps.home_page_is_displayed()"},"keyword":"Then "},{"result":{"status":"passed"},"line":24,"name":"Card are displayed","match":{"location":"stepDefinitions.MainSteps.card_are_displayed()"},"keyword":"And "}],"tags":[{"name":"@tag"},{"name":"@RegressionTest"},{"name":"@SmokeTest"},{"name":"@Mortgage"}]},{"line":4,"name":"","description":"","type":"background","keyword":"Background","steps":[{"result":{"status":"passed"},"line":5,"name":"launch the browser from config variables","match":{"location":"stepDefinitions.MainSteps.launch_the_browser_from_config_variables()"},"keyword":"When "},{"result":{"duration":1002800,"status":"passed"},"line":6,"name":"hit the home page url of banking site","match":{"location":"stepDefinitions.MainSteps.hit_the_home_page_url_of_banking_site()"},"keyword":"And "}]},{"start_timestamp":"2024-12-15T08:59:42.541Z","before":[{"result":{"status":"passed"},"match":{"location":"stepDefinitions.hooks.getDataForMortage()"}}],"line":29,"name":"Userpage login multiple users","description":"","id":"application-login;userpage-login-multiple-users;;3","after":[{"result":{"status":"passed"},"match":{"location":"stepDefinitions.hooks.tear()"}}],"type":"scenario","keyword":"Scenario Outline","steps":[{"result":{"duration":999400,"status":"passed"},"line":21,"name":"User is on NetBanking login page","match":{"location":"stepDefinitions.MainSteps.user_is_not_net_banking_login_page()"},"keyword":"Given "},{"result":{"status":"passed"},"line":22,"name":"User login into application with creditUser and password \"cred123\"","match":{"arguments":[{"val":"creditUser","offset":33},{"val":"\"cred123\"","offset":57}],"location":"stepDefinitions.MainSteps.user_login_into_application_with_and_password(java.lang.String,java.lang.String)"},"keyword":"When "},{"result":{"status":"passed"},"line":23,"name":"Home Page is displayed","match":{"location":"stepDefinitions.MainSteps.home_page_is_displayed()"},"keyword":"Then "},{"result":{"status":"passed"},"line":24,"name":"Card are displayed","match":{"location":"stepDefinitions.MainSteps.card_are_displayed()"},"keyword":"And "}],"tags":[{"name":"@tag"},{"name":"@RegressionTest"},{"name":"@SmokeTest"},{"name":"@Mortgage"}]}],"name":"Application login","description":"","id":"application-login","keyword":"Feature","uri":"file:src/test/java/features/secondProgram.feature","tags":[{"name":"@tag","type":"Tag","location":{"line":1,"column":1}}]}]